cloudplatform_sdks/__init__.py
cloudplatform_sdks/alicloud_models/__init__.py
cloudplatform_sdks/alicloud_models/cdn.py
cloudplatform_sdks/alicloud_models/cs.py
cloudplatform_sdks/alicloud_models/dds.py
cloudplatform_sdks/alicloud_models/ess.py
cloudplatform_sdks/alicloud_models/kafka.py
cloudplatform_sdks/alicloud_models/nas.py
cloudplatform_sdks/alicloud_models/nat.py
cloudplatform_sdks/alicloud_models/r_kvstore.py
cloudplatform_sdks/alicloud_models/vpc.py
cloudplatform_sdks/alicloud_models/vpn.py
cloudplatform_sdks/alicloud_models/clients/__init__.py
cloudplatform_sdks/alicloud_models/clients/cdn_client.py
cloudplatform_sdks/alicloud_models/clients/client.py
cloudplatform_sdks/alicloud_models/clients/constants.py
cloudplatform_sdks/alicloud_models/clients/cs_client.py
cloudplatform_sdks/alicloud_models/clients/dds_client.py
cloudplatform_sdks/alicloud_models/clients/ess_client.py
cloudplatform_sdks/alicloud_models/clients/kafka_client.py
cloudplatform_sdks/alicloud_models/clients/nas_client.py
cloudplatform_sdks/alicloud_models/clients/nat_client.py
cloudplatform_sdks/alicloud_models/clients/order_client.py
cloudplatform_sdks/alicloud_models/clients/r_kvstore_client.py
cloudplatform_sdks/alicloud_models/clients/vpc_client.py
cloudplatform_sdks/alicloud_models/clients/vpn_client.py
cloudplatform_sdks/awscloud_models/__init__.py
cloudplatform_sdks/awscloud_models/clients/__init__.py
cloudplatform_sdks/awscloud_models/clients/client.py
cloudplatform_sdks/awscloud_models/clients/ec2_client.py
cloudplatform_sdks/awscloud_models/clients/load_balancer_client.py
cloudplatform_sdks/cas_models/__init__.py
cloudplatform_sdks/cas_models/ecs.py
cloudplatform_sdks/cas_models/clients/__init__.py
cloudplatform_sdks/cas_models/clients/client.py
cloudplatform_sdks/cas_models/clients/ecs_client.py
cloudplatform_sdks/huaweicloud_models/__init__.py
cloudplatform_sdks/huaweicloud_models/ecs.py
cloudplatform_sdks/huaweicloud_models/eip.py
cloudplatform_sdks/huaweicloud_models/evs.py
cloudplatform_sdks-0.0.62.dist-info/LICENSE
cloudplatform_sdks-0.0.62.dist-info/METADATA
cloudplatform_sdks-0.0.62.dist-info/WHEEL
cloudplatform_sdks-0.0.62.dist-info/top_level.txt
cloudplatform_sdks-0.0.62.dist-info/RECORD
