Metadata-Version: 2.1
Name: cloudplatform-sdks
Version: 0.0.62
Summary: SDK for platforms
Home-page: https://github.com/
Author: cloudchef
Author-email: yuhui.yan@cloudchef.io
License: Apache License
Platform: all
Classifier: Programming Language :: Python :: 3.6
Classifier: Programming Language :: Python :: 3.7
Classifier: Programming Language :: Python :: 3.8
License-File: LICENSE
Requires-Dist: tencentcloud-sdk-python (==3.0.423)
Requires-Dist: aliyun-python-sdk-core (==2.13.35)
Requires-Dist: aliyun-python-sdk-cdn (==3.6.4)
Requires-Dist: aliyun-python-sdk-nas (==3.11.0)
Requires-Dist: aliyun-python-sdk-dds (==3.5.4)
Requires-Dist: aliyun-python-sdk-bss (==0.0.4)
Requires-Dist: aliyun-python-sdk-vpc (==3.0.15)
Requires-Dist: aliyun-python-sdk-ess (==2.3.3)
Requires-Dist: aliyun-python-sdk-cs (==4.8.1)
Requires-Dist: aliyun-python-sdk-r-kvstore (==2.4.0)
Requires-Dist: aliyun-python-sdk-bssopenapi (==1.7.7)
Requires-Dist: aliyun-python-sdk-ecs (==4.24.11)
Requires-Dist: proxy-tools (==0.1.0)
Requires-Dist: huaweicloudsdkcore (==3.0.49)
Requires-Dist: huaweicloudsdkecs (==3.0.49)
Requires-Dist: huaweicloudsdkeip (==3.0.49)
Requires-Dist: huaweicloudsdkevs (==3.0.49)
Requires-Dist: huaweicloudsdkiam (==3.0.49)
Requires-Dist: huaweicloudsdkims (==3.0.49)
Requires-Dist: huaweicloudsdkvpc (==3.0.49)
Requires-Dist: huaweicloudsdkbss (==3.0.51)
Requires-Dist: huaweicloudsdkrds (==3.0.68)
Requires-Dist: huaweicloudsdkdcs (==3.0.70)
